makuo.py
makuo-0.4.dist-info/DESCRIPTION.rst
makuo-0.4.dist-info/METADATA
makuo-0.4.dist-info/RECORD
makuo-0.4.dist-info/WHEEL
makuo-0.4.dist-info/metadata.json
makuo-0.4.dist-info/top_level.txt
