Metadata-Version: 2.0
Name: makuo
Version: 0.4
Summary: makuosan client
Home-page: https://github.com/KLab/makuo-py
Author: INADA Naoki
Author-email: songofacandy@gmail.com
License: UNKNOWN
Platform: UNKNOWN
